pytest_golden/__init__.py
pytest_golden/plugin.py
pytest_golden/py.typed
pytest_golden/yaml.py
pytest_golden-1.0.1.dist-info/METADATA
pytest_golden-1.0.1.dist-info/WHEEL
pytest_golden-1.0.1.dist-info/entry_points.txt
pytest_golden-1.0.1.dist-info/licenses/LICENSE.md
pytest_golden-1.0.1.dist-info/RECORD
