Metadata-Version: 2.4
Name: pytest-golden
Version: 1.0.1
Summary: Plugin for pytest that offloads expected outputs to data files
Project-URL: Documentation, https://github.com/oprypin/pytest-golden#readme
Project-URL: Source, https://github.com/oprypin/pytest-golden
Project-URL: Issues, https://github.com/oprypin/pytest-golden/issues
Author-email: Oleh Prypin <oleh@pryp.in>
License-Expression: MIT
License-File: LICENSE.md
Keywords: pytest,pytest-plugin
Classifier: Development Status :: 5 - Production/Stable
Classifier: Framework :: Pytest
Classifier: Intended Audience :: Developers
Classifier: License :: OSI Approved :: MIT License
Classifier: Operating System :: OS Independent
Classifier: Programming Language :: Python
Classifier: Programming Language :: Python :: 3.9
Classifier: Programming Language :: Python :: 3.10
Classifier: Programming Language :: Python :: 3.11
Classifier: Programming Language :: Python :: 3.12
Classifier: Programming Language :: Python :: 3.13
Classifier: Topic :: Software Development :: Testing :: Unit
Classifier: Typing :: Typed
Requires-Python: >=3.9
Requires-Dist: pytest>=6.1.2
Requires-Dist: ruamel-yaml<1.0,>=0.16.12
Requires-Dist: testfixtures>=6.15.0
